up_ansible/__init__.py
up_ansible/run_for_prompt.py
up_ansible-0.2.18.dist-info/METADATA
up_ansible-0.2.18.dist-info/WHEEL
up_ansible-0.2.18.dist-info/RECORD
